excai_sdk/__init__.py
excai_sdk/_base_client.py
excai_sdk/_client.py
excai_sdk/_compat.py
excai_sdk/_constants.py
excai_sdk/_exceptions.py
excai_sdk/_files.py
excai_sdk/_models.py
excai_sdk/_qs.py
excai_sdk/_resource.py
excai_sdk/_response.py
excai_sdk/_streaming.py
excai_sdk/_types.py
excai_sdk/_version.py
excai_sdk/py.typed
excai_sdk/_utils/__init__.py
excai_sdk/_utils/_compat.py
excai_sdk/_utils/_datetime_parse.py
excai_sdk/_utils/_logs.py
excai_sdk/_utils/_proxy.py
excai_sdk/_utils/_reflection.py
excai_sdk/_utils/_resources_proxy.py
excai_sdk/_utils/_streams.py
excai_sdk/_utils/_sync.py
excai_sdk/_utils/_transform.py
excai_sdk/_utils/_typing.py
excai_sdk/_utils/_utils.py
excai_sdk/lib/.keep
excai_sdk/resources/__init__.py
excai_sdk/resources/assistants.py
excai_sdk/resources/audio.py
excai_sdk/resources/batches.py
excai_sdk/resources/completions.py
excai_sdk/resources/embeddings.py
excai_sdk/resources/files.py
excai_sdk/resources/images.py
excai_sdk/resources/models.py
excai_sdk/resources/moderations.py
excai_sdk/resources/responses.py
excai_sdk/resources/uploads.py
excai_sdk/resources/videos.py
excai_sdk/resources/chat/__init__.py
excai_sdk/resources/chat/chat.py
excai_sdk/resources/chat/completions.py
excai_sdk/resources/chatkit/__init__.py
excai_sdk/resources/chatkit/chatkit.py
excai_sdk/resources/chatkit/sessions.py
excai_sdk/resources/chatkit/threads.py
excai_sdk/resources/containers/__init__.py
excai_sdk/resources/containers/containers.py
excai_sdk/resources/containers/files.py
excai_sdk/resources/conversations/__init__.py
excai_sdk/resources/conversations/conversations.py
excai_sdk/resources/conversations/items.py
excai_sdk/resources/evals/__init__.py
excai_sdk/resources/evals/evals.py
excai_sdk/resources/evals/runs/__init__.py
excai_sdk/resources/evals/runs/output_items.py
excai_sdk/resources/evals/runs/runs.py
excai_sdk/resources/fine_tuning/__init__.py
excai_sdk/resources/fine_tuning/fine_tuning.py
excai_sdk/resources/fine_tuning/jobs.py
excai_sdk-1.3.0.dist-info/METADATA
excai_sdk-1.3.0.dist-info/WHEEL
excai_sdk-1.3.0.dist-info/licenses/LICENSE
excai_sdk-1.3.0.dist-info/RECORD
